customshowme/__init__.py
customshowme/core.py
customshowme-1.0.11.dist-info/AUTHORS
customshowme-1.0.11.dist-info/LICENSE
customshowme-1.0.11.dist-info/METADATA
customshowme-1.0.11.dist-info/NOTICE
customshowme-1.0.11.dist-info/WHEEL
customshowme-1.0.11.dist-info/top_level.txt
customshowme-1.0.11.dist-info/RECORD
