Metadata-Version: 2.1
Name: customshowme
Version: 1.0.11
Summary: Painless Debugging and Inspection for Python
Home-page: http://github.com/a-t-0/customshowme
Author: Navdeep Gill
Author-email: mr.navdeepgill@gmail.com
License: MIT
Classifier: Development Status :: 5 - Production/Stable
Classifier: Environment :: Console
Classifier: Intended Audience :: Developers
Classifier: License :: OSI Approved :: MIT License
Classifier: Programming Language :: Python
Classifier: Programming Language :: Python :: 2.5
Classifier: Programming Language :: Python :: 2.6
Classifier: Programming Language :: Python :: 2.7
Classifier: Operating System :: MacOS :: MacOS X
Classifier: Operating System :: Unix
Classifier: Operating System :: POSIX
Classifier: Topic :: Software Development
Classifier: Topic :: Software Development :: Libraries
Classifier: Topic :: Software Development :: Libraries :: Python Modules
License-File: LICENSE
License-File: NOTICE
License-File: AUTHORS
Requires-Dist: colorama (>=0.1.18)
Requires-Dist: decorator (>=3.2.0)
